nb_functools/__init__.py
nb_functools/_version.py
nb_functools/nb_functools.py
nb_functools-0.7.0.dist-info/AUTHORS.rst
nb_functools-0.7.0.dist-info/LICENSE
nb_functools-0.7.0.dist-info/METADATA
nb_functools-0.7.0.dist-info/WHEEL
nb_functools-0.7.0.dist-info/top_level.txt
nb_functools-0.7.0.dist-info/RECORD
