Metadata-Version: 2.1
Name: nb-functools
Version: 0.7.0
Summary: A package containing useful functions for data wrangling and data analysis of biophysics experiments in a Jupyter notebook
Home-page: https://github.com/bfulroth/nb_functools
Author: Ben Fulroth
Author-email: fulrothb@icloud.com
License: MIT
Project-URL: Documentation, https://nb_functools.readthedocs.io/
Project-URL: Changelog, https://nb_functools.readthedocs.io/en/latest/changelog.html
Project-URL: Issue Tracker, https://github.com/bfulroth/nb_functools/issues
Classifier: Development Status :: 5 - Production/Stable
Classifier: Intended Audience :: Developers
Classifier: License :: OSI Approved :: MIT License
Classifier: Operating System :: Unix
Classifier: Operating System :: POSIX
Classifier: Operating System :: Microsoft :: Windows
Classifier: Programming Language :: Python
Classifier: Programming Language :: Python :: 3
Classifier: Programming Language :: Python :: 3 :: Only
Classifier: Programming Language :: Python :: 3.6
Classifier: Programming Language :: Python :: 3.7
Classifier: Programming Language :: Python :: 3.8
Classifier: Programming Language :: Python :: 3.9
Classifier: Programming Language :: Python :: 3.10
Classifier: Programming Language :: Python :: Implementation :: CPython
Classifier: Programming Language :: Python :: Implementation :: PyPy
Classifier: Topic :: Utilities
Requires-Python: >=3.6
License-File: LICENSE
License-File: AUTHORS.rst
Requires-Dist: pandas >=2.2
Requires-Dist: numpy
Requires-Dist: scipy
Requires-Dist: matplotlib
